python_package_template_cfs/__init__.py
python_package_template_cfs/calculator.py
python_package_template_cfs-0.4.0.dist-info/LICENSE
python_package_template_cfs-0.4.0.dist-info/METADATA
python_package_template_cfs-0.4.0.dist-info/WHEEL
python_package_template_cfs-0.4.0.dist-info/top_level.txt
python_package_template_cfs-0.4.0.dist-info/RECORD
